torch_frft/__init__.py
torch_frft/dfrft_module.py
torch_frft/frft_module.py
torch_frft/layer.py
torch_frft-0.8.1.dist-info/licenses/LICENSE
torch_frft-0.8.1.dist-info/METADATA
torch_frft-0.8.1.dist-info/WHEEL
torch_frft-0.8.1.dist-info/top_level.txt
torch_frft-0.8.1.dist-info/RECORD
