Metadata-Version: 2.4
Name: torch-frft
Version: 0.8.1
Summary: PyTorch implementation of the fractional Fourier transform with trainable transform order.
Author-email: Tuna Alikaşifoğlu <tunakasif@gmail.com>
Classifier: Programming Language :: Python :: 3 :: Only
Classifier: Programming Language :: Python :: 3.10
Classifier: Programming Language :: Python :: 3.11
Classifier: Programming Language :: Python :: 3.12
Classifier: Programming Language :: Python :: 3.13
Requires-Python: <3.14,>=3.10
License-File: LICENSE
Requires-Dist: numpy>=1.22.4
Requires-Dist: scipy>=1.13.1
Requires-Dist: torch>=2
Dynamic: license-file
